ysshd/__init__.py
ysshd/sshd.py
ysshd-0.1.0.dist-info/METADATA
ysshd-0.1.0.dist-info/WHEEL
ysshd-0.1.0.dist-info/entry_points.txt
ysshd-0.1.0.dist-info/RECORD
