Metadata-Version: 2.4
Name: ysshd
Version: 0.1.0
Summary: yet another ssh daemon
Requires-Python: >=3.10
Requires-Dist: asyncssh>=2.20.0
Requires-Dist: bcrypt>=4.0.0
Requires-Dist: fire>=0.5.0
Requires-Dist: loguru>=0.7.3
